{
  "width": 1600,
  "height": 2066,
  "transformacion": "qr",
  "advertencias": [
    "El QR no coincide con el examen esperado"
  ],
  "preguntas": [
    {
      "numeroPregunta": 25,
      "mejorOpcion": "A",
      "mejorScore": 0.9574193685583136,
      "segundoScore": 0.5575682151918094,
      "delta": 0.3998511533665041,
      "dobleMarcada": false,
      "suficiente": false,
      "dx": -4,
      "dy": 0,
      "scoreMean": 0.4888410998777711,
      "scoreStd": 0.25571748560901436,
      "scoreThreshold": 0.6422715912431797,
      "centros": [
        {
          "letra": "A",
          "x": 1449.3356746651652,
          "y": 332.4063681229792,
          "score": 0.9574193685583136
        },
        {
          "letra": "B",
          "x": 1446.7210904930303,
          "y": 338.0339408073607,
          "score": 0.5575682151918094
        },
        {
          "letra": "C",
          "x": 1450.1113706931337,
          "y": 350.75778185990436,
          "score": 0.2457716327227135
        },
        {
          "letra": "D",
          "x": 1450.5066079409116,
          "y": 356.57972537400144,
          "score": 0.3539296710569059
        },
        {
          "letra": "E",
          "x": 1449.9068972810342,
          "y": 368.50165233138296,
          "score": 0.3295166118591132
        }
      ]
    },
    {
      "numeroPregunta": 26,
      "mejorOpcion": "E",
      "mejorScore": 1.0280817901927644,
      "segundoScore": 0.7299261748913833,
      "delta": 0.298155615301381,
      "dobleMarcada": false,
      "suficiente": false,
      "dx": -4,
      "dy": 0,
      "scoreMean": 0.57363103424483,
      "scoreStd": 0.29038523570292474,
      "scoreThreshold": 0.7478621756665849,
      "centros": [
        {
          "letra": "A",
          "x": 1424.117593512061,
          "y": 516.0704510878963,
          "score": 0.49587698371151623
        },
        {
          "letra": "B",
          "x": 1425.584097596433,
          "y": 518.0975610058349,
          "score": 0.45304333346654563
        },
        {
          "letra": "C",
          "x": 1424.0568459983224,
          "y": 526.218731205403,
          "score": 0.16122688896194032
        },
        {
          "letra": "D",
          "x": 1424.5359649359707,
          "y": 537.4358629549657,
          "score": 0.7299261748913833
        },
        {
          "letra": "E",
          "x": 1425.0215840524108,
          "y": 544.7509091116839,
          "score": 1.0280817901927644
        }
      ]
    },
    {
      "numeroPregunta": 27,
      "mejorOpcion": "E",
      "mejorScore": 1.2217451398861732,
      "segundoScore": 0.5042621760750429,
      "delta": 0.7174829638111303,
      "dobleMarcada": false,
      "suficiente": false,
      "dx": -4,
      "dy": 2,
      "scoreMean": 0.6310185368622818,
      "scoreStd": 0.2959813533893696,
      "scoreThreshold": 0.8086073488959036,
      "centros": [
        {
          "letra": "A",
          "x": 1424.7859137780526,
          "y": 753.7144056990194,
          "score": 0.5042621760750429
        },
        {
          "letra": "B",
          "x": 1425.2687640684544,
          "y": 774.7852802613436,
          "score": 0.5034433949128073
        },
        {
          "letra": "C",
          "x": 1425.7584940608006,
          "y": 794.1278786590015,
          "score": 0.4543514926722724
        },
        {
          "letra": "D",
          "x": 1426.2552518441648,
          "y": 801.7480498853959,
          "score": 0.47129048076511304
        },
        {
          "letra": "E",
          "x": 1426.7591897885957,
          "y": 829.6518120171964,
          "score": 1.2217451398861732
        }
      ]
    },
    {
      "numeroPregunta": 28,
      "mejorOpcion": "B",
      "mejorScore": 0.5330796043469614,
      "segundoScore": 0.39650224407179663,
      "delta": 0.13657736027516482,
      "dobleMarcada": false,
      "suficiente": false,
      "dx": -3,
      "dy": 1,
      "scoreMean": 0.40656144796388005,
      "scoreStd": 0.06547055175689145,
      "scoreThreshold": 0.4458437790180149,
      "centros": [
        {
          "letra": "A",
          "x": 1453.9961396141236,
          "y": 966.0309096935206,
          "score": 0.3456107470332812
        },
        {
          "letra": "B",
          "x": 1452.5638958558538,
          "y": 984.7611693086939,
          "score": 0.5330796043469614
        },
        {
          "letra": "C",
          "x": 1455.140366824849,
          "y": 1003.748228653933,
          "score": 0.3846538305290558
        },
        {
          "letra": "D",
          "x": 1453.7257547219144,
          "y": 1023.9980460467715,
          "score": 0.39650224407179663
        },
        {
          "letra": "E",
          "x": 1454.3202680519494,
          "y": 1031.5167655695245,
          "score": 0.3729608138383052
        }
      ]
    },
    {
      "numeroPregunta": 29,
      "mejorOpcion": "E",
      "mejorScore": 0.9956228331693119,
      "segundoScore": 0.5235631828465286,
      "delta": 0.4720596503227833,
      "dobleMarcada": false,
      "suficiente": false,
      "dx": -10,
      "dy": 10,
      "scoreMean": 0.3038372032031681,
      "scoreStd": 0.4009483762553126,
      "scoreThreshold": 0.5444062289563556,
      "centros": [
        {
          "letra": "A",
          "x": 1452.8759086659202,
          "y": 1241.7913485143624,
          "score": 0.5235631828465286
        },
        {
          "letra": "B",
          "x": 1449.529685411364,
          "y": 1256.6139550195578,
          "score": 0
        },
        {
          "letra": "C",
          "x": 1448.1942397104963,
          "y": 1287.845763865079,
          "score": 0
        },
        {
          "letra": "D",
          "x": 1448.8698402812813,
          "y": 1309.4969777391448,
          "score": 0
        },
        {
          "letra": "E",
          "x": 1453.556764849851,
          "y": 1343.578141352238,
          "score": 0.9956228331693119
        }
      ]
    },
    {
      "numeroPregunta": 30,
      "mejorOpcion": "A",
      "mejorScore": 1.0235304931545293,
      "segundoScore": 0.6479621448522586,
      "delta": 0.3755683483022707,
      "dobleMarcada": false,
      "suficiente": false,
      "dx": -1,
      "dy": 1,
      "scoreMean": 0.5497886677391902,
      "scoreStd": 0.3015677872717617,
      "scoreThreshold": 0.7307293401022472,
      "centros": [
        {
          "letra": "A",
          "x": 1427.8571428571431,
          "y": 1568.5278876527086,
          "score": 1.0235304931545293
        },
        {
          "letra": "B",
          "x": 1425.634320904378,
          "y": 1619.8847857044925,
          "score": 0.6479621448522586
        },
        {
          "letra": "C",
          "x": 1429.4254706302506,
          "y": 1644.9492203802208,
          "score": 0.5744408228133765
        },
        {
          "letra": "D",
          "x": 1442.2309722148023,
          "y": 1685.7404442915783,
          "score": 0.3965776937173348
        },
        {
          "letra": "E",
          "x": 1428.0512197576484,
          "y": 1736.2784149482,
          "score": 0.10643218415845179
        }
      ]
    },
    {
      "numeroPregunta": 31,
      "mejorOpcion": "B",
      "mejorScore": 0.2864699916526433,
      "segundoScore": 0.1670395294967596,
      "delta": 0.11943046215588371,
      "dobleMarcada": false,
      "suficiente": false,
      "dx": 18,
      "dy": 8,
      "scoreMean": 0.11210783778763142,
      "scoreStd": 0.10453180864667594,
      "scoreThreshold": 0.17482692297563698,
      "centros": [
        {
          "letra": "A",
          "x": 1475.0794413713286,
          "y": 1936.1989106125595,
          "score": 0.08335102112034376
        },
        {
          "letra": "B",
          "x": 1475.9952494843976,
          "y": 1983.0851091423474,
          "score": 0.2864699916526433
        },
        {
          "letra": "C",
          "x": 1488.928966458586,
          "y": 2022.8099582174111,
          "score": 0.1670395294967596
        },
        {
          "letra": "D",
          "x": 1485.8811227994968,
          "y": 2067.398300780608,
          "score": 0.023678646668410422
        },
        {
          "letra": "E",
          "x": 1478.8522701749093,
          "y": 2116.8759707742024,
          "score": 0
        }
      ]
    }
  ]
}