[
  {
    "file": "q01_A_1428_465.png",
    "numeroPregunta": 1,
    "letra": "A",
    "x": 1455.8660130718954,
    "y": 492.72450805008947,
    "score": 0.7289836064563588,
    "confianzaPregunta": 0.6487234757407718,
    "seleccionada": true,
    "opcionDetectada": "A"
  },
  {
    "file": "q01_B_1426_470.png",
    "numeroPregunta": 1,
    "letra": "B",
    "x": 1453.8660130718954,
    "y": 497.9555635062611,
    "score": 0.628966405574914,
    "confianzaPregunta": 0.6487234757407718,
    "seleccionada": false,
    "opcionDetectada": "A"
  },
  {
    "file": "q01_C_1424_495.png",
    "numeroPregunta": 1,
    "letra": "C",
    "x": 1451.8660130718954,
    "y": 523.1866189624329,
    "score": 0.0810746563207822,
    "confianzaPregunta": 0.6487234757407718,
    "seleccionada": false,
    "opcionDetectada": "A"
  },
  {
    "file": "q01_D_1426_508.png",
    "numeroPregunta": 1,
    "letra": "D",
    "x": 1453.8660130718954,
    "y": 536.4176744186047,
    "score": 0.21750244262113244,
    "confianzaPregunta": 0.6487234757407718,
    "seleccionada": false,
    "opcionDetectada": "A"
  },
  {
    "file": "q01_E_1424_512.png",
    "numeroPregunta": 1,
    "letra": "E",
    "x": 1451.8660130718954,
    "y": 539.6487298747764,
    "score": 0.2817090756406426,
    "confianzaPregunta": 0.6487234757407718,
    "seleccionada": false,
    "opcionDetectada": "A"
  },
  {
    "file": "q02_A_1415_660.png",
    "numeroPregunta": 2,
    "letra": "A",
    "x": 1443.3660130718954,
    "y": 688.0554561717352,
    "score": 0.512092621203204,
    "confianzaPregunta": 1,
    "seleccionada": true,
    "opcionDetectada": "A"
  },
  {
    "file": "q02_B_1415_669.png",
    "numeroPregunta": 2,
    "letra": "B",
    "x": 1443.3660130718954,
    "y": 696.6044364937388,
    "score": 0.16698671014087801,
    "confianzaPregunta": 1,
    "seleccionada": false,
    "opcionDetectada": "A"
  },
  {
    "file": "q02_C_1423_691.png",
    "numeroPregunta": 2,
    "letra": "C",
    "x": 1451.3660130718954,
    "y": 719.1534168157425,
    "score": 0.10097934560785805,
    "confianzaPregunta": 1,
    "seleccionada": false,
    "opcionDetectada": "A"
  },
  {
    "file": "q02_D_1421_704.png",
    "numeroPregunta": 2,
    "letra": "D",
    "x": 1449.3660130718954,
    "y": 731.702397137746,
    "score": 0.26539560916122334,
    "confianzaPregunta": 1,
    "seleccionada": false,
    "opcionDetectada": "A"
  },
  {
    "file": "q02_E_1421_724.png",
    "numeroPregunta": 2,
    "letra": "E",
    "x": 1449.3660130718954,
    "y": 752.2513774597495,
    "score": 0.09874563828478303,
    "confianzaPregunta": 1,
    "seleccionada": false,
    "opcionDetectada": "A"
  },
  {
    "file": "q03_A_1424_883.png",
    "numeroPregunta": 3,
    "letra": "A",
    "x": 1452.3660130718954,
    "y": 911.3864042933811,
    "score": 0.11395421721872123,
    "confianzaPregunta": 0.31127974805844055,
    "seleccionada": false,
    "opcionDetectada": "B"
  },
  {
    "file": "q03_B_1424_897.png",
    "numeroPregunta": 3,
    "letra": "B",
    "x": 1452.3660130718954,
    "y": 924.6883005366725,
    "score": 0.26100143072138543,
    "confianzaPregunta": 0.31127974805844055,
    "seleccionada": true,
    "opcionDetectada": "B"
  },
  {
    "file": "q03_C_1426_918.png",
    "numeroPregunta": 3,
    "letra": "C",
    "x": 1454.3660130718954,
    "y": 945.9901967799642,
    "score": 0.17574952304236235,
    "confianzaPregunta": 0.31127974805844055,
    "seleccionada": false,
    "opcionDetectada": "B"
  },
  {
    "file": "q03_D_1424_939.png",
    "numeroPregunta": 3,
    "letra": "D",
    "x": 1452.3660130718954,
    "y": 967.2920930232559,
    "score": 0.2269121238257386,
    "confianzaPregunta": 0.31127974805844055,
    "seleccionada": false,
    "opcionDetectada": "B"
  },
  {
    "file": "q03_E_1424_941.png",
    "numeroPregunta": 3,
    "letra": "E",
    "x": 1452.3660130718954,
    "y": 968.5939892665475,
    "score": 0.22735386044248815,
    "confianzaPregunta": 0.31127974805844055,
    "seleccionada": false,
    "opcionDetectada": "B"
  },
  {
    "file": "q04_A_1397_1099.png",
    "numeroPregunta": 4,
    "letra": "A",
    "x": 1425.3766666666666,
    "y": 1127.3148479427548,
    "score": 0.23951831672896468,
    "confianzaPregunta": 1,
    "seleccionada": false,
    "opcionDetectada": "D"
  },
  {
    "file": "q04_B_1397_1120.png",
    "numeroPregunta": 4,
    "letra": "B",
    "x": 1425.3766666666666,
    "y": 1147.538103756708,
    "score": 0.22259889736566646,
    "confianzaPregunta": 1,
    "seleccionada": false,
    "opcionDetectada": "D"
  },
  {
    "file": "q04_C_1397_1142.png",
    "numeroPregunta": 4,
    "letra": "C",
    "x": 1425.3766666666666,
    "y": 1169.7613595706619,
    "score": 0.2800361155373939,
    "confianzaPregunta": 1,
    "seleccionada": false,
    "opcionDetectada": "D"
  },
  {
    "file": "q04_D_1391_1168.png",
    "numeroPregunta": 4,
    "letra": "D",
    "x": 1419.3766666666666,
    "y": 1195.9846153846154,
    "score": 0.4413218737227505,
    "confianzaPregunta": 1,
    "seleccionada": true,
    "opcionDetectada": "D"
  },
  {
    "file": "q04_E_1393_1186.png",
    "numeroPregunta": 4,
    "letra": "E",
    "x": 1421.3766666666666,
    "y": 1214.207871198569,
    "score": 0.06649391132739793,
    "confianzaPregunta": 1,
    "seleccionada": false,
    "opcionDetectada": "D"
  },
  {
    "file": "q05_A_1425_1287.png",
    "numeroPregunta": 5,
    "letra": "A",
    "x": 1453.3660130718954,
    "y": 1315.4472271914133,
    "score": 0.19617290060350318,
    "confianzaPregunta": 0.3544785213205707,
    "seleccionada": false,
    "opcionDetectada": "C"
  },
  {
    "file": "q05_B_1425_1324.png",
    "numeroPregunta": 5,
    "letra": "B",
    "x": 1453.3660130718954,
    "y": 1352.4308407871197,
    "score": 0.20913036778116048,
    "confianzaPregunta": 0.3544785213205707,
    "seleccionada": false,
    "opcionDetectada": "C"
  },
  {
    "file": "q05_C_1425_1345.png",
    "numeroPregunta": 5,
    "letra": "C",
    "x": 1453.3660130718954,
    "y": 1373.4144543828265,
    "score": 0.2677461769140583,
    "confianzaPregunta": 0.3544785213205707,
    "seleccionada": true,
    "opcionDetectada": "C"
  },
  {
    "file": "q05_D_1421_1376.png",
    "numeroPregunta": 5,
    "letra": "D",
    "x": 1449.3660130718954,
    "y": 1404.398067978533,
    "score": 0.18351494443693542,
    "confianzaPregunta": 0.3544785213205707,
    "seleccionada": false,
    "opcionDetectada": "C"
  },
  {
    "file": "q05_E_1421_1397.png",
    "numeroPregunta": 5,
    "letra": "E",
    "x": 1449.3660130718954,
    "y": 1425.3816815742398,
    "score": 0.13225482720728404,
    "confianzaPregunta": 0.3544785213205707,
    "seleccionada": false,
    "opcionDetectada": "C"
  },
  {
    "file": "q06_A_1421_1495.png",
    "numeroPregunta": 6,
    "letra": "A",
    "x": 1448.8660130718954,
    "y": 1522.9141323792487,
    "score": 0.12232088253174345,
    "confianzaPregunta": 0,
    "seleccionada": false,
    "opcionDetectada": null
  },
  {
    "file": "q06_B_1421_1516.png",
    "numeroPregunta": 6,
    "letra": "B",
    "x": 1448.8660130718954,
    "y": 1544.1396064400717,
    "score": 0.1785878149572056,
    "confianzaPregunta": 0,
    "seleccionada": false,
    "opcionDetectada": null
  },
  {
    "file": "q06_C_1421_1539.png",
    "numeroPregunta": 6,
    "letra": "C",
    "x": 1448.8660130718954,
    "y": 1567.3650805008947,
    "score": 0.20484310957590324,
    "confianzaPregunta": 0,
    "seleccionada": false,
    "opcionDetectada": null
  },
  {
    "file": "q06_D_1415_1567.png",
    "numeroPregunta": 6,
    "letra": "D",
    "x": 1442.8660130718954,
    "y": 1594.5905545617175,
    "score": 0.1764076351810984,
    "confianzaPregunta": 0,
    "seleccionada": false,
    "opcionDetectada": null
  },
  {
    "file": "q06_E_1413_1588.png",
    "numeroPregunta": 6,
    "letra": "E",
    "x": 1440.8660130718954,
    "y": 1615.81602862254,
    "score": 0.12414141867192936,
    "confianzaPregunta": 0,
    "seleccionada": false,
    "opcionDetectada": null
  },
  {
    "file": "q07_A_1424_1651.png",
    "numeroPregunta": 7,
    "letra": "A",
    "x": 1451.8660130718954,
    "y": 1679.4508050089444,
    "score": 0.13535292996344553,
    "confianzaPregunta": 0,
    "seleccionada": false,
    "opcionDetectada": null
  },
  {
    "file": "q07_B_1424_1665.png",
    "numeroPregunta": 7,
    "letra": "B",
    "x": 1451.8660130718954,
    "y": 1692.6370661896244,
    "score": 0.2581818191001658,
    "confianzaPregunta": 0,
    "seleccionada": false,
    "opcionDetectada": null
  },
  {
    "file": "q07_C_1424_1686.png",
    "numeroPregunta": 7,
    "letra": "C",
    "x": 1451.8660130718954,
    "y": 1713.823327370304,
    "score": 0.19437047198349927,
    "confianzaPregunta": 0,
    "seleccionada": false,
    "opcionDetectada": null
  },
  {
    "file": "q07_D_1424_1705.png",
    "numeroPregunta": 7,
    "letra": "D",
    "x": 1451.8660130718954,
    "y": 1733.009588550984,
    "score": 0.20963828852063027,
    "confianzaPregunta": 0,
    "seleccionada": false,
    "opcionDetectada": null
  },
  {
    "file": "q07_E_1424_1726.png",
    "numeroPregunta": 7,
    "letra": "E",
    "x": 1451.8660130718954,
    "y": 1754.1958497316634,
    "score": 0.2730504989190038,
    "confianzaPregunta": 0,
    "seleccionada": false,
    "opcionDetectada": null
  }
]